{"_links": {"self": {"href": "http://compras.dados.gov.br/comprasContratos/doc/contrato/131728/itens_compras_contratos.json", "title": "Lista de itens_compras_contratos"}, "first": {"href": "/comprasContratos/doc/contrato/131728/itens_compras_contratos.json?offset=0", "title": "Primeira p\u00e1gina"}}, "_embedded": {"itens_compras_contratos": [{"id": 828039, "contrato_id": 131728, "tipo_id": "Servi\u00e7o", "grupo_id": "GRUPO GENERICO SERVICO", "catmatser_item_id": "3417 - DESINSETIZA\u00c7\u00c3O , DESRATIZA\u00c7\u00c3O , DEDETIZA\u00c7\u00c3O", "descricao_complementar": "DESINSETIZA\u00c7\u00c3O / DESRATIZA\u00c7\u00c3O / DEDETIZA\u00c7\u00c3O", "quantidade": 3, "valor_unitario": 1972.46, "valor_total": 5917.38, "_links": {"self": {"href": "/comprasContratos/id/contrato/131728/itens_compras_contratos/828039", "title": "Item referente ao contrato: 131728"}, "contrato": {"href": "/comprasContratos/id/contrato/131728", "title": "Contrato 131728"}}}]}, "count": 1, "offset": 0}