{"_links": {"self": {"href": "http://compras.dados.gov.br/comprasContratos/doc/contrato/153744/itens_compras_contratos.json", "title": "Lista de itens_compras_contratos"}, "first": {"href": "/comprasContratos/doc/contrato/153744/itens_compras_contratos.json?offset=0", "title": "Primeira p\u00e1gina"}}, "_embedded": {"itens_compras_contratos": [{"id": 948729, "contrato_id": 153744, "tipo_id": "Servi\u00e7o", "grupo_id": "GRUPO GENERICO SERVICO", "catmatser_item_id": "26077 - SOFTWARE COMO SERVICO - SAAS", "descricao_complementar": "SOFTWARE COMO SERVICO - SAAS", "quantidade": 1, "valor_unitario": 5185944.65, "valor_total": 5185944.65, "_links": {"self": {"href": "/comprasContratos/id/contrato/153744/itens_compras_contratos/948729", "title": "Item referente ao contrato: 153744"}, "contrato": {"href": "/comprasContratos/id/contrato/153744", "title": "Contrato 153744"}}}, {"id": 948730, "contrato_id": 153744, "tipo_id": "Servi\u00e7o", "grupo_id": "GRUPO GENERICO SERVICO", "catmatser_item_id": "27502 - CESS\u00c3O TEMPOR\u00c1RIA DE DIREITOS SOBRE PROGRAMAS DE COMPUTADOR LOCA\u00c7\u00c3O DE SOFTWARE", "descricao_complementar": "CESS\u00c3O TEMPOR\u00c1RIA DE DIREITOS SOBRE PROGRAMAS DE COMPUTADOR LOCA\u00c7\u00c3O DE SOFTWARE", "quantidade": 1, "valor_unitario": 203394.48, "valor_total": 203394.48, "_links": {"self": {"href": "/comprasContratos/id/contrato/153744/itens_compras_contratos/948730", "title": "Item referente ao contrato: 153744"}, "contrato": {"href": "/comprasContratos/id/contrato/153744", "title": "Contrato 153744"}}}]}, "count": 2, "offset": 0}