{"_links": {"self": {"href": "http://compras.dados.gov.br/comprasContratos/doc/contrato/154415/itens_compras_contratos.json", "title": "Lista de itens_compras_contratos"}, "first": {"href": "/comprasContratos/doc/contrato/154415/itens_compras_contratos.json?offset=0", "title": "Primeira p\u00e1gina"}}, "_embedded": {"itens_compras_contratos": [{"id": 951344, "contrato_id": 154415, "tipo_id": "Servi\u00e7o", "grupo_id": "GRUPO GENERICO SERVICO", "catmatser_item_id": "15830 - APRESENTA\u00c7\u00c3O ART\u00cdSTICA / MUSICAL / CANTO / CORAL", "descricao_complementar": "APRESENTA\u00c7\u00c3O ART\u00cdSTICA / MUSICAL / CANTO / CORAL", "quantidade": 1, "valor_unitario": 43200.0, "valor_total": 43200.0, "_links": {"self": {"href": "/comprasContratos/id/contrato/154415/itens_compras_contratos/951344", "title": "Item referente ao contrato: 154415"}, "contrato": {"href": "/comprasContratos/id/contrato/154415", "title": "Contrato 154415"}}}]}, "count": 1, "offset": 0}