{"codigo": 423249, "descricao": "DESINFETANTE, COMPOSI\u00c7\u00c3O \u00c0 BASE DE FEN\u00d3IS SINT\u00c9TICOS: O-BENZIL-P-CLOROFENOL  PRINC\u00cdPIO ATIVO ORTO-FENILFENOL E P-T\u00c9RCIO-BUTILFENOL  FORMA F\u00cdSICA SOLU\u00c7\u00c3O AQUOSA CONCENTRADA", "id_grupo": 68, "id_classe": 6840, "id_pdm": "14487", "status": true, "sustentavel": false, "_links": {"self": {"href": "/materiais/id/material/423249", "title": "Material 423249: DESINFETANTE, COMPOSI\u00c7\u00c3O \u00c0 BASE DE FEN\u00d3IS SINT\u00c9TICOS: O-BENZIL-P-CLOROFENOL  PRINC\u00cdPIO ATIVO ORTO-FENILFENOL E P-T\u00c9RCIO-BUTILFENOL  FORMA F\u00cdSICA SOLU\u00c7\u00c3O AQUOSA CONCENTRADA"}, "classe": {"href": "/materiais/id/classe/6840", "title": "Classe 6840: PESTICIDAS E DESINFETANTES                                                                                              "}, "grupo": {"href": "/materiais/id/grupo/68", "title": "Grupo 68: SUBST\u00c2NCIAS E PRODUTOS QU\u00cdMICOS                                                                                         "}, "irps": {"href": "/licitacoes/v1/irps?item_material=423249", "title": "Inten\u00e7\u00f5es de registro de pre\u00e7o que incluem este item de material."}, "licitacoes": {"href": "/licitacoes/v1/licitacoes?item_material=423249", "title": "Licita\u00e7\u00f5es que incluem este item de material."}, "pdm": {"href": "/materiais/id/pdm/14487", "title": "PDM 14487: DESINFETANTE                                                                                        "}, "unidade_medida": {"href": "/materiais/v1/unidadesfornecimento?co_material=423249", "title": "Unidades de fornecimento deste item de material."}}}