{"codigo": 5274, "descricao": "ESTRADO DE CARGA ( PALETE ), ESTRADO DE CARGA ( PALETE ) NOME", "id_grupo": 39, "id_classe": 3990, "id_pdm": "07181", "status": false, "sustentavel": false, "_links": {"self": {"href": "/materiais/id/material/5274", "title": "Material 5274: ESTRADO DE CARGA ( PALETE ), ESTRADO DE CARGA ( PALETE ) NOME"}, "classe": {"href": "/materiais/id/classe/3990", "title": "Classe 3990: EQUIPAMENTOS DIVERSOS PARA MOVIMENTA\u00c7\u00c3O DE MATERIAIS                                                                    "}, "grupo": {"href": "/materiais/id/grupo/39", "title": "Grupo 39: EQUIPAMENTOS PARA MANUSEIO DE MATERIAL                                                                                  "}, "irps": {"href": "/licitacoes/v1/irps?item_material=5274", "title": "Inten\u00e7\u00f5es de registro de pre\u00e7o que incluem este item de material."}, "licitacoes": {"href": "/licitacoes/v1/licitacoes?item_material=5274", "title": "Licita\u00e7\u00f5es que incluem este item de material."}, "pdm": {"href": "/materiais/id/pdm/07181", "title": "PDM 07181: ESTRADO DE CARGA ( PALETE )                                                                         "}, "unidade_medida": {"href": "/materiais/v1/unidadesfornecimento?co_material=5274", "title": "Unidades de fornecimento deste item de material."}}}